c2_overlay/__init__.py
c2_overlay/__main__.py
c2_overlay/align.py
c2_overlay/ass_lint.py
c2_overlay/cli.py
c2_overlay/core.py
c2_overlay/ffmpeg.py
c2_overlay/fit.py
c2_overlay/overlay.py
c2_overlay/timeutil.py
c2_overlay/video.py
c2_overlay-0.2.0.dist-info/METADATA
c2_overlay-0.2.0.dist-info/WHEEL
c2_overlay-0.2.0.dist-info/entry_points.txt
c2_overlay-0.2.0.dist-info/top_level.txt
c2_overlay-0.2.0.dist-info/RECORD
