Metadata-Version: 2.4
Name: c2-overlay
Version: 0.2.0
Summary: generate PM5-style overlays for rowing videos from Concept2 FIT files
Author: banteg
Requires-Python: >=3.12
Requires-Dist: fitparse>=1.2.0
